nonebot_plugin_super_resolution/__init__.py
nonebot_plugin_super_resolution/enhance.py
nonebot_plugin_super_resolution-0.1.1.dist-info/WHEEL
nonebot_plugin_super_resolution-0.1.1.dist-info/METADATA
nonebot_plugin_super_resolution-0.1.1.dist-info/licenses/LICENSE
nonebot_plugin_super_resolution-0.1.1.dist-info/RECORD
