Metadata-Version: 2.1
Name: nonebot-plugin-super-resolution
Version: 0.1.1
Summary: NoneBot2 plugin for anime image super resolution
License: MIT
Author-email: Akirami <Akiramiaya@outlook.com>
Requires-Python: >=3.8
Requires-Dist: Pillow<10.0.0,>=9.2.0
Requires-Dist: httpx>=0.23.0
Requires-Dist: nonebot-adapter-onebot>=2.1.3
Requires-Dist: nonebot2>=2.0.0rc1
Project-URL: Homepage, https://github.com/A-kirami/nonebot-plugin-super-resolution
Project-URL: Repository, https://github.com/A-kirami/nonebot-plugin-super-resolution
